toc2md/__init__.py
toc2md/__main__.py
toc2md/docs/toc2md.pdf
toc2md-0.9.5.dist-info/entry_points.txt
toc2md-0.9.5.dist-info/WHEEL
toc2md-0.9.5.dist-info/METADATA
toc2md-0.9.5.dist-info/RECORD
