Metadata-Version: 2.1
Name: toc2md
Version: 0.9.5
Summary: Insert or update nested chapter numbering and linked Table Of Contents into a MarkDown file
Home-page: https://pypi.org/project/toc2md
License: UNKNOWN
Author: Carlo Alessandro Verre
Author-email: carlo.alessandro.verre@gmail.com
Requires-Python: >=3.7
Classifier: Programming Language :: Python :: 3
Classifier: Programming Language :: Python :: 3.7
Classifier: Development Status :: 4 - Beta
Classifier: Environment :: Console
Classifier: Intended Audience :: End Users/Desktop
Classifier: License :: OSI Approved :: GNU General Public License v3 or later (GPLv3+)
Classifier: Operating System :: POSIX :: Linux
Requires-Dist: libfunx
